<xml xmlns:o="urn:schemas-microsoft-com:office:office">
 <o:MainFile HRef="::maker_web.htm"/>
 <o:File HRef="error.htm"/>
 <o:File HRef="frame.htm"/>
 <o:File HRef="next_active.gif"/>
 <o:File HRef="next_disabled.gif"/>
 <o:File HRef="prev_active.gif"/>
 <o:File HRef="prev_disabled.gif"/>
 <o:File HRef="outline_collapse.gif"/>
 <o:File HRef="outline_expand.gif"/>
 <o:File HRef="notes_flag.gif"/>
 <o:File HRef="fullscr.gif"/>
 <o:File HRef="fullscrClose.gif"/>
 <o:File HRef="narration.gif"/>
 <o:File HRef="navbg.gif"/>
 <o:File HRef="outline.gif"/>
 <o:File HRef="space.gif"/>
 <o:File HRef="blank_notes.htm"/>
 <o:File HRef="endshow.htm"/>
 <o:File HRef="navigation_bar.htm"/>
 <o:File HRef="fullscreen.htm"/>
 <o:File HRef="fs_navigation_bar.htm"/>
 <o:File HRef="outline_navigation_bar.htm"/>
 <o:File HRef="outline_collapsed.htm"/>
 <o:File HRef="outline_expanded.htm"/>
 <o:File HRef="slide0017.htm"/>
 <o:File HRef="slide0018.htm"/>
 <o:File HRef="slide0019.htm"/>
 <o:File HRef="slide0020.htm"/>
 <o:File HRef="slide0021.htm"/>
 <o:File HRef="slide0022.htm"/>
 <o:File HRef="slide0023.htm"/>
 <o:File HRef="slide0024.htm"/>
 <o:File HRef="script.js"/>
 <o:File HRef="filelist.xml"/>
</xml>